{
  "products": [
    {
      "name": "Wardrobe 1",
      "price": 100,
      "color": "Brown",
      "dimensions": {"length": "1.5", "width": "0.6", "height": "2.0"},
      "description": "A spacious brown wardrobe with 2 doors and 3 shelves.",
      "image": "https://via.placeholder.com/150"
    },
    {
      "name": "Wardrobe 2",
      "price": 120,
      "color": "White",
      "dimensions": {"length": "1.5", "width": "0.7", "height": "2.1"},
      "description": "A white wardrobe with a modern design and ample storage space.",
      "image": "https://via.placeholder.com/150"
    },
    {
      "name": "Wardrobe 3",
      "price": 90,
      "color": "Black",
      "dimensions": {"length": "1.4", "width": "0.6", "height": "1.9"},
      "description": "A compact black wardrobe, ideal for small spaces.",
      "image": "https://via.placeholder.com/150"
    },
    {
      "name": "Wardrobe 4",
      "price": 150,
      "color": "Grey",
      "dimensions": {"length": "1.8", "width": "0.75", "height": "2.2"},
      "description": "A large grey wardrobe with a sliding door and full-length mirror.",
      "image": "https://via.placeholder.com/150"
    },
    {
      "name": "Wardrobe 5",
      "price": 130,
      "color": "Beige",
      "dimensions": {"length": "1.6", "width": "0.7", "height": "2.0"},
      "description": "A beige wardrobe with 3 compartments for easy organization.",
      "image": "https://via.placeholder.com/150"
    },
    {
      "name": "Wardrobe 6",
      "price": 200,
      "color": "Dark Wood",
      "dimensions": {"length": "1.7", "width": "0.8", "height": "2.3"},
      "description": "A premium dark wood wardrobe with a rich finish and 4 drawers.",
      "image": "https://via.placeholder.com/150"
    },
    {
      "name": "Wardrobe 7",
      "price": 110,
      "color": "Walnut",
      "dimensions": {"length": "1.6", "width": "0.65", "height": "2.1"},
      "description": "A walnut-colored wardrobe with a classic look.",
      "image": "https://via.placeholder.com/150"
    },
    {
      "name": "Wardrobe 8",
      "price": 160,
      "color": "Mahogany",
      "dimensions": {"length": "1.8", "width": "0.8", "height": "2.4"},
      "description": "A large mahogany wardrobe with multiple hanging spaces.",
      "image": "https://via.placeholder.com/150"
    },
    {
      "name": "Wardrobe 9",
      "price": 140,
      "color": "White Oak",
      "dimensions": {"length": "1.7", "width": "0.75", "height": "2.2"},
      "description": "A sturdy white oak wardrobe with open shelving and hanging rods.",
      "image": "https://via.placeholder.com/150"
    },
    {
      "name": "Wardrobe 10",
      "price": 125,
      "color": "Pine",
      "dimensions": {"length": "1.6", "width": "0.7", "height": "2.0"},
      "description": "A simple pine wardrobe with two compartments for storage.",
      "image": "https://via.placeholder.com/150"
    },
    {
      "name": "Wardrobe 11",
      "price": 180,
      "color": "Light Brown",
      "dimensions": {"length": "1.8", "width": "0.75", "height": "2.3"},
      "description": "A light brown wardrobe with elegant detailing and 5 shelves.",
      "image": "https://via.placeholder.com/150"
    },
    {
      "name": "Wardrobe 12",
      "price": 170,
      "color": "Chestnut",
      "dimensions": {"length": "1.7", "width": "0.8", "height": "2.3"},
      "description": "A stylish chestnut wardrobe with a combination of drawers and hanging spaces.",
      "image": "https://via.placeholder.com/150"
    },
    {
      "name": "Wardrobe 13",
      "price": 160,
      "color": "Maple",
      "dimensions": {"length": "1.7", "width": "0.75", "height": "2.0"},
      "description": "A practical maple wardrobe with a minimalist design.",
      "image": "https://via.placeholder.com/150"
    },
    {
      "name": "Wardrobe 14",
      "price": 140,
      "color": "Ash",
      "dimensions": {"length": "1.5", "width": "0.65", "height": "2.0"},
      "description": "A durable ash wardrobe that fits comfortably in smaller rooms.",
      "image": "https://via.placeholder.com/150"
    },
    {
      "name": "Wardrobe 15",
      "price": 110,
      "color": "Teak",
      "dimensions": {"length": "1.6", "width": "0.7", "height": "2.1"},
      "description": "A teak wardrobe with a solid build and adjustable shelves.",
      "image": "https://via.placeholder.com/150"
    },
    {
      "name": "Wardrobe 16",
      "price": 180,
      "color": "Ebony",
      "dimensions": {"length": "1.8", "width": "0.75", "height": "2.2"},
      "description": "A premium ebony wardrobe with sleek, modern styling.",
      "image": "https://via.placeholder.com/150"
    },
    {
      "name": "Wardrobe 17",
      "price": 220,
      "color": "Dark Oak",
      "dimensions": {"length": "1.9", "width": "0.8", "height": "2.5"},
      "description": "An elegant dark oak wardrobe with glass doors and deep drawers.",
      "image": "https://via.placeholder.com/150"
    },
    {
      "name": "Wardrobe 18",
      "price": 190,
      "color": "Cherry Wood",
      "dimensions": {"length": "1.8", "width": "0.75", "height": "2.3"},
      "description": "A cherry wood wardrobe with rich texture and practical design.",
      "image": "https://via.placeholder.com/150"
    },
    {
      "name": "Wardrobe 19",
      "price": 210,
      "color": "Walnut Brown",
      "dimensions": {"length": "1.8", "width": "0.8", "height": "2.4"},
      "description": "A spacious walnut brown wardrobe with adjustable shelves.",
      "image": "https://via.placeholder.com/150"
    },
    {
      "name": "Wardrobe 20",
      "price": 230,
      "color": "Mahogany Red",
      "dimensions": {"length": "1.9", "width": "0.85", "height": "2.5"},
      "description": "A luxurious mahogany red wardrobe with deep drawers and wide hanging spaces.",
      "image": "https://via.placeholder.com/150"
    }
  ]
}
